{
  "name": "Peasy.nu Intranet",
  "subtitle": "All you need to know about running Peasy.nu",
  "description": "Here we keep everything about running this business documented to enable anybody to run this business",
  "footer": "Pål ❤ Ida",
  "url": "https://intranet.peasy.nu",
  "githubUrl": "https://github.com/pal/peasy-intranet",
  "githubBranch": "main",
  "navigationStyle": "vertical",
  "emoji": "💥",
  "enableSearch": true,
  "enableDarkMode": true,
  "enableEditButton": true,
  "enableDatestamp": true,
  "enableGithubLink": true,
  "enableContact": false,
  "enableNetlifyCMS": true,
  "enableComments": false,
  "enableEncryption": false,
  "enablePageNavigation": true
}
